modoboa_sievefilters/__init__.py
modoboa_sievefilters/apps.py
modoboa_sievefilters/constants.py
modoboa_sievefilters/forms.py
modoboa_sievefilters/handlers.py
modoboa_sievefilters/imaputils.py
modoboa_sievefilters/lib.py
modoboa_sievefilters/mocks.py
modoboa_sievefilters/modo_extension.py
modoboa_sievefilters/rfc6266.py
modoboa_sievefilters/tests.py
modoboa_sievefilters/urls.py
modoboa_sievefilters/views.py
modoboa_sievefilters/locale/cs_CZ/LC_MESSAGES/django.mo
modoboa_sievefilters/locale/cs_CZ/LC_MESSAGES/django.po
modoboa_sievefilters/locale/cs_CZ/LC_MESSAGES/djangojs.mo
modoboa_sievefilters/locale/cs_CZ/LC_MESSAGES/djangojs.po
modoboa_sievefilters/locale/de/LC_MESSAGES/django.mo
modoboa_sievefilters/locale/de/LC_MESSAGES/django.po
modoboa_sievefilters/locale/de/LC_MESSAGES/djangojs.mo
modoboa_sievefilters/locale/de/LC_MESSAGES/djangojs.po
modoboa_sievefilters/locale/el_GR/LC_MESSAGES/django.mo
modoboa_sievefilters/locale/el_GR/LC_MESSAGES/django.po
modoboa_sievefilters/locale/el_GR/LC_MESSAGES/djangojs.mo
modoboa_sievefilters/locale/el_GR/LC_MESSAGES/djangojs.po
modoboa_sievefilters/locale/en/LC_MESSAGES/django.mo
modoboa_sievefilters/locale/en/LC_MESSAGES/django.po
modoboa_sievefilters/locale/en/LC_MESSAGES/djangojs.mo
modoboa_sievefilters/locale/en/LC_MESSAGES/djangojs.po
modoboa_sievefilters/locale/es/LC_MESSAGES/django.mo
modoboa_sievefilters/locale/es/LC_MESSAGES/django.po
modoboa_sievefilters/locale/es/LC_MESSAGES/djangojs.mo
modoboa_sievefilters/locale/es/LC_MESSAGES/djangojs.po
modoboa_sievefilters/locale/fr/LC_MESSAGES/django.mo
modoboa_sievefilters/locale/fr/LC_MESSAGES/django.po
modoboa_sievefilters/locale/fr/LC_MESSAGES/djangojs.mo
modoboa_sievefilters/locale/fr/LC_MESSAGES/djangojs.po
modoboa_sievefilters/locale/it/LC_MESSAGES/django.mo
modoboa_sievefilters/locale/it/LC_MESSAGES/django.po
modoboa_sievefilters/locale/it/LC_MESSAGES/djangojs.mo
modoboa_sievefilters/locale/it/LC_MESSAGES/djangojs.po
modoboa_sievefilters-1.7.0.dist-info/LICENSE
modoboa_sievefilters-1.7.0.dist-info/METADATA
modoboa_sievefilters-1.7.0.dist-info/WHEEL
modoboa_sievefilters-1.7.0.dist-info/top_level.txt
modoboa_sievefilters-1.7.0.dist-info/RECORD
